README.md
setup.py
general_methods/__init__.py
general_methods/constants.py
general_methods/country_codes.py
general_methods/exceptions.py
general_methods/response.py
general_methods/utils.py
general_methods/validators.py
general_methods.egg-info/PKG-INFO
general_methods.egg-info/SOURCES.txt
general_methods.egg-info/dependency_links.txt
general_methods.egg-info/requires.txt
general_methods.egg-info/top_level.txt