Metadata-Version: 2.1
Name: general-methods
Version: 0.0.2
Summary: A small general methods.
Home-page: https://github.com/vishalanandl177/General-Methods
Author: Vishal Anand
Author-email: vishalanandl177@gmail.com
License: GNU General Public License v3.0
Platform: UNKNOWN
Classifier: Programming Language :: Python :: 3.5
Classifier: Programming Language :: Python :: 3.6
Classifier: Programming Language :: Python :: 3.7
Classifier: Programming Language :: Python :: 3.8
Classifier: License :: OSI Approved :: MIT License
Classifier: Operating System :: OS Independent
Requires-Python: >=3.5
